python_mpesawrapper/__init__.py
python_mpesawrapper/b2b.py
python_mpesawrapper/b2c.py
python_mpesawrapper/c2b.py
python_mpesawrapper/common.py
python_mpesawrapper/mpesaExpress.py
python_mpesawrapper/reversals.py
python_mpesawrapper/statusQuery.py
python_mpesawrapper-1.0.4.dist-info/METADATA
python_mpesawrapper-1.0.4.dist-info/RECORD
python_mpesawrapper-1.0.4.dist-info/WHEEL
python_mpesawrapper-1.0.4.dist-info/top_level.txt
